transstellar_antd/__init__.py
transstellar_antd/components/__init__.py
transstellar_antd/components/anchor.py
transstellar_antd/components/badge.py
transstellar_antd/components/breadcrumb.py
transstellar_antd/components/button.py
transstellar_antd/components/checkbox.py
transstellar_antd/components/collapse.py
transstellar_antd/components/color_picker.py
transstellar_antd/components/date_picker.py
transstellar_antd/components/form.py
transstellar_antd/components/form_item.py
transstellar_antd/components/input.py
transstellar_antd/components/menu.py
transstellar_antd/components/message.py
transstellar_antd/components/modal.py
transstellar_antd/components/page.py
transstellar_antd/components/popover.py
transstellar_antd/components/popover_confirm.py
transstellar_antd/components/radio_group.py
transstellar_antd/components/row.py
transstellar_antd/components/select.py
transstellar_antd/components/spin.py
transstellar_antd/components/switch.py
transstellar_antd/components/tab.py
transstellar_antd/components/table.py
transstellar_antd/components/text_area.py
transstellar_antd/components/upload.py
transstellar_antd/v4/__init__.py
transstellar_antd/v4/components/badge.py
transstellar_antd/v4/components/breadcrumb.py
transstellar_antd/v4/components/button.py
transstellar_antd/v4/components/checkbox.py
transstellar_antd/v4/components/collapse.py
transstellar_antd/v4/components/date_picker.py
transstellar_antd/v4/components/form.py
transstellar_antd/v4/components/form_item.py
transstellar_antd/v4/components/input.py
transstellar_antd/v4/components/menu.py
transstellar_antd/v4/components/message.py
transstellar_antd/v4/components/modal.py
transstellar_antd/v4/components/page.py
transstellar_antd/v4/components/popover.py
transstellar_antd/v4/components/popover_confirm.py
transstellar_antd/v4/components/radio_group.py
transstellar_antd/v4/components/row.py
transstellar_antd/v4/components/select.py
transstellar_antd/v4/components/spin.py
transstellar_antd/v4/components/switch.py
transstellar_antd-0.19.4.dist-info/METADATA
transstellar_antd-0.19.4.dist-info/WHEEL
transstellar_antd-0.19.4.dist-info/RECORD
