Metadata-Version: 2.1
Name: transstellar-antd
Version: 0.19.4
Summary: A ant design component for pytest based on transstellar framework.
Author: Onramplab Dev
Author-email: dev@onramplab.com
Requires-Python: >=3.12,<4.0
Classifier: Programming Language :: Python :: 3
Classifier: Programming Language :: Python :: 3.12
Classifier: Programming Language :: Python :: 3.13
Requires-Dist: selenium (>=4.18.1,<5.0.0)
Requires-Dist: transstellar (>=3.10.5,<4.0.0)
